wafer_core/__init__.py
wafer_core/async_ssh.py
wafer_core/auth.py
wafer_core/gpu.py
wafer_core/gpu_detect.py
wafer_core/problem_config.py
wafer_core/remote_env.py
wafer_core/remote_jobs.py
wafer_core/retry.py
wafer_core/ssh.py
wafer_core/config/__init__.py
wafer_core/config/loader.py
wafer_core/config/schema.py
wafer_core/environments/__init__.py
wafer_core/environments/coding.py
wafer_core/environments/gpumode.py
wafer_core/lib/__init__.py
wafer_core/lib/kernel_scope/__init__.py
wafer_core/lib/kernel_scope/api.py
wafer_core/lib/kernel_scope/amdgcn/__init__.py
wafer_core/lib/kernel_scope/amdgcn/analyzer.py
wafer_core/lib/kernel_scope/amdgcn/instruction_db.py
wafer_core/lib/kernel_scope/amdgcn/parser.py
wafer_core/lib/kernel_scope/amdgcn/types.py
wafer_core/lib/kernel_scope/correlation/__init__.py
wafer_core/lib/kernel_scope/correlation/mapper.py
wafer_core/lib/kernel_scope/llvm_ir/__init__.py
wafer_core/lib/kernel_scope/llvm_ir/analyzer.py
wafer_core/lib/kernel_scope/llvm_ir/parser.py
wafer_core/lib/kernel_scope/llvm_ir/types.py
wafer_core/lib/kernel_scope/metrics/__init__.py
wafer_core/lib/kernel_scope/metrics/occupancy.py
wafer_core/lib/kernel_scope/targets/__init__.py
wafer_core/lib/kernel_scope/targets/specs.py
wafer_core/lib/kernel_scope/ttgir/__init__.py
wafer_core/lib/kernel_scope/ttgir/analyzer.py
wafer_core/lib/kernel_scope/ttgir/parser.py
wafer_core/lib/kernel_scope/ttgir/types.py
wafer_core/lib/nsys/__init__.py
wafer_core/lib/nsys/analysis.py
wafer_core/lib/nsys/discovery.py
wafer_core/lib/nsys/export.py
wafer_core/lib/nsys/extraction.py
wafer_core/lib/nsys/main.py
wafer_core/lib/nsys/parsing.py
wafer_core/lib/perfetto/__init__.py
wafer_core/lib/perfetto/build_trace_processor.py
wafer_core/lib/perfetto/perfetto_tool.py
wafer_core/lib/perfetto/trace_manager.py
wafer_core/lib/perfetto/trace_processor.py
wafer_core/lib/rocprofiler/__init__.py
wafer_core/lib/rocprofiler/compute/__init__.py
wafer_core/lib/rocprofiler/compute/analyzer.py
wafer_core-0.1.38.dist-info/METADATA
wafer_core-0.1.38.dist-info/WHEEL
wafer_core-0.1.38.dist-info/RECORD
