Metadata-Version: 2.4
Name: wafer-core
Version: 0.1.38
Summary: Core utilities and environments for Wafer GPU kernel optimization
Requires-Python: >=3.10
Requires-Dist: aiohttp>=3.9.0
Requires-Dist: anthropic>=0.40.0
Requires-Dist: anyio>=4.0.0
Requires-Dist: astunparse==1.6.2
Requires-Dist: asyncssh>=2.14.0
Requires-Dist: colorlover>=0.3.0
Requires-Dist: dacite>=1.8.0
Requires-Dist: dash-bootstrap-components>=1.0.0
Requires-Dist: dash-svg>=0.0.11
Requires-Dist: dash>=3.0.0
Requires-Dist: dnspython>=2.8.0
Requires-Dist: httpx>=0.25.0
Requires-Dist: ijson>=3.2.0
Requires-Dist: kaleido==0.2.1
Requires-Dist: markdownify>=0.11.0
Requires-Dist: matplotlib>=3.0.0
Requires-Dist: modal>=0.64.0
Requires-Dist: numpy>=1.17.5
Requires-Dist: openai>=1.0.0
Requires-Dist: orjson>=3.9.0
Requires-Dist: pandas~=3.0.0
Requires-Dist: paramiko>=3.0.0
Requires-Dist: paramiko>=3.4.0
Requires-Dist: plotext>=5.3.2
Requires-Dist: plotille>=5.0.0
Requires-Dist: pymongo>=4.16.0
Requires-Dist: python-dotenv>=1.0.0
Requires-Dist: pyyaml>=6.0
Requires-Dist: setuptools
Requires-Dist: supabase>=2.27.1
Requires-Dist: tabulate>=0.8.0
Requires-Dist: textual-fspicker>=0.6.0
Requires-Dist: textual-plotext>=1.0.0
Requires-Dist: textual>=7.0.0
Requires-Dist: tqdm>=4.0.0
Requires-Dist: trio-asyncio>=0.15.0
Requires-Dist: trio>=0.24.0
Provides-Extra: dev
Requires-Dist: pytest-asyncio>=0.21.0; extra == 'dev'
Requires-Dist: pytest>=7.0.0; extra == 'dev'
Requires-Dist: ruff>=0.1.0; extra == 'dev'
